{"cameraMode":{"drawMode":0,"name":"Shaded","section":"Shading Mode"},"sceneLighting":true,"audioPlay":false,"sceneViewState":{"m_AlwaysRefresh":false,"showFog":true,"showSkybox":true,"showFlares":true,"showImageEffects":true,"showParticleSystems":true,"showVisualEffectGraphs":true,"m_FxEnabled":true},"in2DMode":false,"pivot":{"x":543.8829956054688,"y":131.9099884033203,"z":-22.555435180664064},"rotation":{"x":0.04676228016614914,"y":0.0359480194747448,"z":-0.0016840392490848899,"w":0.9982572793960571},"size":320.69305419921877,"orthographic":false}